{"is_source_file": true, "format": "JavaScript (React JSX)", "description": "This file defines a React component 'RecipeList' for displaying, searching, filtering, and managing a list of recipes in a web application. It includes UI elements for creating, viewing, editing, and deleting recipes, and handles fetching data from external APIs.", "external_files": ["../utils/api", "react", "react-router-dom"], "external_methods": ["apiGet", "apiDelete", "useNavigate", "useEffect", "useState"], "published": ["RecipeList"], "classes": [], "methods": [{"name": "handleDelete(id)", "description": "Handles deletion of a recipe after user confirmation, updates local recipes state upon successful deletion.", "scope": "RecipeList", "scopeKind": "function"}, {"name": "RecipeList()", "scope": "", "scopeKind": "", "description": "unavailable"}], "calls": ["react", "useNavigate", "apiGet", "apiDelete", "setRecipes", "setCategories", "setError", "navigate", "window.confirm", "setRecipes", "alert"], "search-terms": ["RecipeList", "recipe listing", "recipe management", "React hooks", "fetch recipes", "filter recipes", "delete recipe", "recipe categories", "subrecipes", "UI buttons"], "state": 2, "file_id": 17, "knowledge_revision": 52, "git_revision": "9b034a452cd2ffb6a96c6883ed791128535472a8", "revision_history": [{"35": ""}, {"52": "9b034a452cd2ffb6a96c6883ed791128535472a8"}], "ctags": [{"_type": "tag", "name": "RecipeList", "path": "/home/kavia/workspace/code-generation/recipe-share-platform-54397-54486/recipe_frontend/src/pages/RecipeList.js", "pattern": "/^function RecipeList() {$/", "language": "JavaScript", "kind": "function", "signature": "()"}, {"_type": "tag", "name": "category", "path": "/home/kavia/workspace/code-generation/recipe-share-platform-54397-54486/recipe_frontend/src/pages/RecipeList.js", "pattern": "/^          value={category}$/", "language": "JavaScript", "kind": "field", "scope": "RecipeList.value", "scopeKind": "class"}, {"_type": "tag", "name": "e", "path": "/home/kavia/workspace/code-generation/recipe-share-platform-54397-54486/recipe_frontend/src/pages/RecipeList.js", "pattern": "/^            onChange={e => setFilter(e.target.value)}$/", "language": "JavaScript", "kind": "property", "scope": "RecipeList.onChange", "scopeKind": "class"}, {"_type": "tag", "name": "e", "path": "/home/kavia/workspace/code-generation/recipe-share-platform-54397-54486/recipe_frontend/src/pages/RecipeList.js", "pattern": "/^          onChange={e => setCategory(e.target.value)}$/", "language": "JavaScript", "kind": "property", "scope": "RecipeList.onChange", "scopeKind": "class"}, {"_type": "tag", "name": "filter", "path": "/home/kavia/workspace/code-generation/recipe-share-platform-54397-54486/recipe_frontend/src/pages/RecipeList.js", "pattern": "/^            value={filter}$/", "language": "JavaScript", "kind": "field", "scope": "RecipeList.value", "scopeKind": "class"}, {"_type": "tag", "name": "handleDelete", "path": "/home/kavia/workspace/code-generation/recipe-share-platform-54397-54486/recipe_frontend/src/pages/RecipeList.js", "pattern": "/^  function handleDelete(id) {$/", "language": "JavaScript", "kind": "function", "signature": "(id)", "scope": "RecipeList", "scopeKind": "function"}, {"_type": "tag", "name": "onChange", "path": "/home/kavia/workspace/code-generation/recipe-share-platform-54397-54486/recipe_frontend/src/pages/RecipeList.js", "pattern": "/^            onChange={e => setFilter(e.target.value)}$/", "language": "JavaScript", "kind": "class", "scope": "RecipeList", "scopeKind": "class"}, {"_type": "tag", "name": "onChange", "path": "/home/kavia/workspace/code-generation/recipe-share-platform-54397-54486/recipe_frontend/src/pages/RecipeList.js", "pattern": "/^          onChange={e => setCategory(e.target.value)}$/", "language": "JavaScript", "kind": "class", "scope": "RecipeList", "scopeKind": "class"}], "hash": "8af04d68597749e931baf00aabff1003", "format-version": 4, "code-base-name": "recipe_frontend", "filename": "recipe_frontend/src/pages/RecipeList.js", "fields": [{"name": "value={category}", "scope": "RecipeList.value", "scopeKind": "class", "description": "unavailable"}, {"name": "onChange={e => setFilter(e.target.value)}", "scope": "RecipeList.onChange", "scopeKind": "class", "description": "unavailable"}, {"name": "onChange={e => setCategory(e.target.value)}", "scope": "RecipeList.onChange", "scopeKind": "class", "description": "unavailable"}, {"name": "value={filter}", "scope": "RecipeList.value", "scopeKind": "class", "description": "unavailable"}]}